README.rst
setup.cfg
setup.py
temp_utils/__init__.py
temp_utils/contextmanagers.py
temp_utils.egg-info/PKG-INFO
temp_utils.egg-info/SOURCES.txt
temp_utils.egg-info/dependency_links.txt
temp_utils.egg-info/requires.txt
temp_utils.egg-info/top_level.txt