Metadata-Version: 1.0
Name: temp-utils
Version: 1.0.0
Summary: A temporary file utilities
Home-page: https://github.com/naphatkrit/temp-utils
Author: Naphat Sanguansin
Author-email: naphat.krit@gmail.com
License: UNKNOWN
Keywords: temporary,temp,chdir,temp_file,tempfile,tempdir,temp_dir
Platform: UNKNOWN
